tidyup/__init__.py
tidyup/tidyup.py
tidyup/utils.py
tidyup-0.0.3.dist-info/LICENSE
tidyup-0.0.3.dist-info/METADATA
tidyup-0.0.3.dist-info/WHEEL
tidyup-0.0.3.dist-info/entry_points.txt
tidyup-0.0.3.dist-info/top_level.txt
tidyup-0.0.3.dist-info/RECORD
