Metadata-Version: 2.1
Name: tidyup
Version: 0.0.3
Summary: Help keep your files and folders tidy by file type or date
Author-email: Esteban Valencia <me@estebanvalencia.com>
Maintainer-email: Esteban Valencia <me@estebanvalencia.com>
License: MIT
Keywords: utility
Classifier: Development Status :: 4 - Beta
Classifier: Intended Audience :: Developers
Classifier: License :: OSI Approved :: MIT License
Classifier: Programming Language :: Python :: 3
Classifier: Topic :: Software Development :: Libraries :: Python Modules
Requires-Python: >=3.9.1
License-File: LICENSE
Requires-Dist: setuptools-scm
